ununennium/__init__.py
ununennium/version.py
ununennium/augmentation/__init__.py
ununennium/augmentation/compose.py
ununennium/augmentation/geometric.py
ununennium/benchmarks/__init__.py
ununennium/benchmarks/profiler.py
ununennium/benchmarks/throughput.py
ununennium/cli/__init__.py
ununennium/cli/main.py
ununennium/core/__init__.py
ununennium/core/band_specs.py
ununennium/core/bounds.py
ununennium/core/crs.py
ununennium/core/exceptions.py
ununennium/core/geobatch.py
ununennium/core/geotensor.py
ununennium/core/transforms.py
ununennium/core/types.py
ununennium/datasets/__init__.py
ununennium/datasets/base.py
ununennium/datasets/synthetic.py
ununennium/export/__init__.py
ununennium/export/onnx.py
ununennium/export/torchscript.py
ununennium/io/__init__.py
ununennium/io/readers.py
ununennium/io/writers.py
ununennium/losses/__init__.py
ununennium/losses/detection.py
ununennium/losses/segmentation.py
ununennium/metrics/__init__.py
ununennium/metrics/detection.py
ununennium/metrics/segmentation.py
ununennium/models/__init__.py
ununennium/models/backbones.py
ununennium/models/heads.py
ununennium/models/layers.py
ununennium/models/registry.py
ununennium/models/architectures/__init__.py
ununennium/models/architectures/change_detection.py
ununennium/models/architectures/detection.py
ununennium/models/architectures/unet.py
ununennium/models/gan/__init__.py
ununennium/models/gan/cyclegan.py
ununennium/models/gan/discriminators.py
ununennium/models/gan/esrgan.py
ununennium/models/gan/generators.py
ununennium/models/gan/losses.py
ununennium/models/gan/pix2pix.py
ununennium/models/pinn/__init__.py
ununennium/models/pinn/base.py
ununennium/models/pinn/collocation.py
ununennium/models/pinn/equations.py
ununennium/preprocessing/__init__.py
ununennium/preprocessing/indices.py
ununennium/preprocessing/normalization.py
ununennium/sensors/__init__.py
ununennium/sensors/landsat.py
ununennium/sensors/sentinel2.py
ununennium/tiling/__init__.py
ununennium/tiling/sampler.py
ununennium-1.0.8.dist-info/METADATA
ununennium-1.0.8.dist-info/WHEEL
ununennium-1.0.8.dist-info/entry_points.txt
ununennium-1.0.8.dist-info/licenses/LICENSE
ununennium-1.0.8.dist-info/licenses/NOTICE.md
ununennium-1.0.8.dist-info/RECORD
