Metadata-Version: 2.4
Name: ununennium
Version: 1.0.8
Summary: Production-grade Python library for satellite and geospatial imagery machine learning
Project-URL: Homepage, https://github.com/olaflaitinen/ununennium
Project-URL: Documentation, https://github.com/olaflaitinen/ununennium/tree/main/docs
Project-URL: Repository, https://github.com/olaflaitinen/ununennium
Project-URL: Issues, https://github.com/olaflaitinen/ununennium/issues
Project-URL: Changelog, https://github.com/olaflaitinen/ununennium/blob/main/CHANGELOG.md
Author: Ununennium Contributors
License-Expression: Apache-2.0
License-File: LICENSE
License-File: NOTICE.md
Keywords: computer-vision,deep-learning,earth-observation,geospatial,gis,machine-learning,remote-sensing,satellite-imagery
Classifier: Development Status :: 3 - Alpha
Classifier: Intended Audience :: Developers
Classifier: Intended Audience :: Science/Research
Classifier: License :: OSI Approved :: Apache Software License
Classifier: Operating System :: OS Independent
Classifier: Programming Language :: Python :: 3
Classifier: Programming Language :: Python :: 3.10
Classifier: Programming Language :: Python :: 3.11
Classifier: Programming Language :: Python :: 3.12
Classifier: Topic :: Scientific/Engineering :: Artificial Intelligence
Classifier: Topic :: Scientific/Engineering :: GIS
Classifier: Topic :: Scientific/Engineering :: Image Processing
Classifier: Typing :: Typed
Requires-Python: >=3.10
Requires-Dist: affine>=2.4.0
Requires-Dist: einops>=0.7.0
Requires-Dist: numpy>=1.24.0
Requires-Dist: torch>=2.4.0
Requires-Dist: typing-extensions>=4.0.0
Provides-Extra: all
Requires-Dist: albumentations>=1.3.0; extra == 'all'
Requires-Dist: fsspec>=2023.1.0; extra == 'all'
Requires-Dist: gcsfs>=2023.1.0; extra == 'all'
Requires-Dist: hydra-core>=1.3.0; extra == 'all'
Requires-Dist: hypothesis>=6.82.0; extra == 'all'
Requires-Dist: mkdocs-gen-files>=0.5.0; extra == 'all'
Requires-Dist: mkdocs-literate-nav>=0.6.0; extra == 'all'
Requires-Dist: mkdocs-material>=9.4.0; extra == 'all'
Requires-Dist: mkdocs>=1.5.0; extra == 'all'
Requires-Dist: mkdocstrings[python]>=0.23.0; extra == 'all'
Requires-Dist: mypy>=1.5.0; extra == 'all'
Requires-Dist: omegaconf>=2.3.0; extra == 'all'
Requires-Dist: onnx>=1.14.0; extra == 'all'
Requires-Dist: onnxscript>=0.1.0; extra == 'all'
Requires-Dist: planetary-computer>=1.0.0; extra == 'all'
Requires-Dist: pre-commit>=3.4.0; extra == 'all'
Requires-Dist: pyproj>=3.5.0; extra == 'all'
Requires-Dist: pyright>=1.1.0; extra == 'all'
Requires-Dist: pystac-client>=0.7.0; extra == 'all'
Requires-Dist: pystac>=1.8.0; extra == 'all'
Requires-Dist: pytest-benchmark>=4.0.0; extra == 'all'
Requires-Dist: pytest-cov>=4.1.0; extra == 'all'
Requires-Dist: pytest-xdist>=3.3.0; extra == 'all'
Requires-Dist: pytest>=7.4.0; extra == 'all'
Requires-Dist: pytorch-lightning>=2.0.0; extra == 'all'
Requires-Dist: rasterio>=1.3.0; extra == 'all'
Requires-Dist: ruff>=0.1.0; extra == 'all'
Requires-Dist: s3fs>=2023.1.0; extra == 'all'
Requires-Dist: segmentation-models-pytorch>=0.3.3; extra == 'all'
Requires-Dist: shapely>=2.0.0; extra == 'all'
Requires-Dist: tensorboard>=2.13.0; extra == 'all'
Requires-Dist: timm>=0.9.0; extra == 'all'
Requires-Dist: torchvision>=0.15.0; extra == 'all'
Requires-Dist: wandb>=0.15.0; extra == 'all'
Requires-Dist: xarray>=2023.1.0; extra == 'all'
Requires-Dist: zarr>=2.16.0; extra == 'all'
Provides-Extra: dev
Requires-Dist: hypothesis>=6.82.0; extra == 'dev'
Requires-Dist: mypy>=1.5.0; extra == 'dev'
Requires-Dist: pre-commit>=3.4.0; extra == 'dev'
Requires-Dist: pyright>=1.1.0; extra == 'dev'
Requires-Dist: pytest-benchmark>=4.0.0; extra == 'dev'
Requires-Dist: pytest-cov>=4.1.0; extra == 'dev'
Requires-Dist: pytest-xdist>=3.3.0; extra == 'dev'
Requires-Dist: pytest>=7.4.0; extra == 'dev'
Requires-Dist: ruff>=0.1.0; extra == 'dev'
Provides-Extra: docs
Requires-Dist: mkdocs-gen-files>=0.5.0; extra == 'docs'
Requires-Dist: mkdocs-literate-nav>=0.6.0; extra == 'docs'
Requires-Dist: mkdocs-material>=9.4.0; extra == 'docs'
Requires-Dist: mkdocs>=1.5.0; extra == 'docs'
Requires-Dist: mkdocstrings[python]>=0.23.0; extra == 'docs'
Provides-Extra: export
Requires-Dist: onnx>=1.14.0; extra == 'export'
Requires-Dist: onnxscript>=0.1.0; extra == 'export'
Provides-Extra: geo
Requires-Dist: pyproj>=3.5.0; extra == 'geo'
Requires-Dist: rasterio>=1.3.0; extra == 'geo'
Requires-Dist: shapely>=2.0.0; extra == 'geo'
Provides-Extra: ml
Requires-Dist: albumentations>=1.3.0; extra == 'ml'
Requires-Dist: segmentation-models-pytorch>=0.3.3; extra == 'ml'
Requires-Dist: timm>=0.9.0; extra == 'ml'
Requires-Dist: torchvision>=0.15.0; extra == 'ml'
Provides-Extra: stac
Requires-Dist: planetary-computer>=1.0.0; extra == 'stac'
Requires-Dist: pystac-client>=0.7.0; extra == 'stac'
Requires-Dist: pystac>=1.8.0; extra == 'stac'
Provides-Extra: training
Requires-Dist: hydra-core>=1.3.0; extra == 'training'
Requires-Dist: omegaconf>=2.3.0; extra == 'training'
Requires-Dist: pytorch-lightning>=2.0.0; extra == 'training'
Requires-Dist: tensorboard>=2.13.0; extra == 'training'
Requires-Dist: wandb>=0.15.0; extra == 'training'
Provides-Extra: zarr
Requires-Dist: fsspec>=2023.1.0; extra == 'zarr'
Requires-Dist: gcsfs>=2023.1.0; extra == 'zarr'
Requires-Dist: s3fs>=2023.1.0; extra == 'zarr'
Requires-Dist: xarray>=2023.1.0; extra == 'zarr'
Requires-Dist: zarr>=2.16.0; extra == 'zarr'
